datasette_enrichments/__init__.py
datasette_enrichments/hookspecs.py
datasette_enrichments/utils.py
datasette_enrichments/views.py
datasette_enrichments/templates/enrichment.html
datasette_enrichments/templates/enrichment_job.html
datasette_enrichments/templates/enrichment_jobs.html
datasette_enrichments/templates/enrichment_picker.html
datasette_enrichments-0.5.1.dist-info/licenses/LICENSE
datasette_enrichments-0.5.1.dist-info/METADATA
datasette_enrichments-0.5.1.dist-info/WHEEL
datasette_enrichments-0.5.1.dist-info/entry_points.txt
datasette_enrichments-0.5.1.dist-info/top_level.txt
datasette_enrichments-0.5.1.dist-info/RECORD
